[
  {
    "split": "eval",
    "baseline": "vanilla",
    "mse": 0.0008325478993356228,
    "mae": 0.011481310240924358,
    "nmse": 0.32293909788131714,
    "relative_nmse_improvement_pct": 0.0
  },
  {
    "split": "eval",
    "baseline": "context_forecast",
    "mse": 0.0008541005081497133,
    "mae": 0.011773769743740559,
    "nmse": 0.3322807550430298,
    "relative_nmse_improvement_pct": -2.8926992416381836
  },
  {
    "split": "eval",
    "baseline": "horizon_knn_weighted",
    "mse": 0.0012542876997475724,
    "mae": 0.017393166561609528,
    "nmse": 0.48473747914093784,
    "relative_nmse_improvement_pct": -50.101824870732436
  },
  {
    "split": "eval",
    "baseline": "horizon_knn_mean",
    "mse": 0.0011355866445228457,
    "mae": 0.016840847209095955,
    "nmse": 0.4374382793903351,
    "relative_nmse_improvement_pct": -35.455345153808594
  },
  {
    "split": "eval",
    "baseline": "residual_knn_weighted",
    "mse": 0.0011341854585455613,
    "mae": 0.014260159316253242,
    "nmse": 0.4379092505812289,
    "relative_nmse_improvement_pct": -35.6011871755969
  },
  {
    "split": "eval",
    "baseline": "horizon_mix_scalar",
    "mse": 0.000819035324844256,
    "mae": 0.011525356735659884,
    "nmse": 0.31906266871939076,
    "relative_nmse_improvement_pct": 1.2003591969378067
  },
  {
    "split": "eval",
    "baseline": "residual_mix_scalar",
    "mse": 0.0008318271062834326,
    "mae": 0.011474666595577776,
    "nmse": 0.3226637325105438,
    "relative_nmse_improvement_pct": 0.08526851427402186
  },
  {
    "split": "eval",
    "baseline": "residual_ridge_shared",
    "mse": 0.0008319230541090053,
    "mae": 0.011476115660299794,
    "nmse": 0.3226971694410697,
    "relative_nmse_improvement_pct": 0.07491457114813727
  },
  {
    "split": "eval",
    "baseline": "residual_ridge_horizon",
    "mse": 0.0008329514530487359,
    "mae": 0.011493266560137272,
    "nmse": 0.3231152594089508,
    "relative_nmse_improvement_pct": -0.054549459367990494
  },
  {
    "split": "eval",
    "baseline": "horizon_ridge_shared",
    "mse": 0.0008164782984413781,
    "mae": 0.01155006958224814,
    "nmse": 0.3194672668138706,
    "relative_nmse_improvement_pct": 1.0750730060943121
  },
  {
    "split": "eval",
    "baseline": "full_ridge_horizon",
    "mse": 0.0008344933739863336,
    "mae": 0.011941706761717796,
    "nmse": 0.3275291919708252,
    "relative_nmse_improvement_pct": -1.4213497638702393
  },
  {
    "split": "eval",
    "baseline": "horizon_mix_scalar_eval_fit",
    "mse": 0.0008181133490424696,
    "mae": 0.011616000606068369,
    "nmse": 0.3190729221242117,
    "relative_nmse_improvement_pct": 1.1971841695446592
  },
  {
    "split": "eval",
    "baseline": "residual_mix_scalar_eval_fit",
    "mse": 0.000831082049819275,
    "mae": 0.011480074021072074,
    "nmse": 0.3223783168527723,
    "relative_nmse_improvement_pct": 0.17364915930710104
  },
  {
    "split": "eval",
    "baseline": "residual_ridge_shared_eval_fit",
    "mse": 0.0008307320387272205,
    "mae": 0.011477941837616553,
    "nmse": 0.32224246475272594,
    "relative_nmse_improvement_pct": 0.21571656487602311
  },
  {
    "split": "eval",
    "baseline": "residual_ridge_horizon_eval_fit",
    "mse": 0.0008242717594839633,
    "mae": 0.011503515765070915,
    "nmse": 0.32104629278182983,
    "relative_nmse_improvement_pct": 0.5861182808876038
  },
  {
    "split": "eval",
    "baseline": "horizon_ridge_shared_eval_fit",
    "mse": 0.0008139746508848812,
    "mae": 0.011660961304576879,
    "nmse": 0.31843573972819633,
    "relative_nmse_improvement_pct": 1.3944914637669017
  },
  {
    "split": "eval",
    "baseline": "full_ridge_horizon_eval_fit",
    "mse": 0.0007829019450582564,
    "mae": 0.011826343834400177,
    "nmse": 0.3113740086555481,
    "relative_nmse_improvement_pct": 3.581198215484619
  }
]